LICENSE
README.rst
setup.py
crown/__init__.py
crown/common.py
crown/crown.py
crown/database.py
crown/eng_taosrestful.py
crown/eng_taosrestful3.py
crown/field.py
crown/query.py
crown.egg-info/PKG-INFO
crown.egg-info/SOURCES.txt
crown.egg-info/dependency_links.txt
crown.egg-info/requires.txt
crown.egg-info/top_level.txt