Metadata-Version: 2.1
Name: crown
Version: 0.3.0
Summary: crown is a simple and small ORM for Time Series Database (TSDB) tdengine(taos), making it easy to learn and intuitive to use.
Home-page: https://github.com/machine-w/crown
Author: machine-w
Author-email: steve2008.ma@gmail.com
Keywords: orm,taos,TDengine,TSDB,Time Series Database,connector,python
Requires-Python: >=3
License-File: LICENSE
